cliexercises/__init__.py
cliexercises/app_guide.md
cliexercises/cli_exercises.css
cliexercises/cli_exercises.py
cliexercises/questions.json
cliexercises/user_progress.json
cliexercises/sample_input/.hidden
cliexercises/sample_input/anchors.txt
cliexercises/sample_input/blocks.txt
cliexercises/sample_input/books.txt
cliexercises/sample_input/c1.txt
cliexercises/sample_input/c2.txt
cliexercises/sample_input/code.txt
cliexercises/sample_input/colors.txt
cliexercises/sample_input/duplicates.txt
cliexercises/sample_input/file_size.txt
cliexercises/sample_input/fruits.txt
cliexercises/sample_input/fun.txt
cliexercises/sample_input/greeting.txt
cliexercises/sample_input/hex.txt
cliexercises/sample_input/ip.txt
cliexercises/sample_input/lines.txt
cliexercises/sample_input/marks_1.csv
cliexercises/sample_input/marks_2.csv
cliexercises/sample_input/multi_empty_lines.txt
cliexercises/sample_input/names.txt
cliexercises/sample_input/nums_1.txt
cliexercises/sample_input/nums_2.txt
cliexercises/sample_input/patterns.txt
cliexercises/sample_input/purchases.txt
cliexercises/sample_input/range.txt
cliexercises/sample_input/replace.txt
cliexercises/sample_input/sample.txt
cliexercises/sample_input/scores.csv
cliexercises/sample_input/shopping_feb.txt
cliexercises/sample_input/shopping_jan.txt
cliexercises/sample_input/table.txt
cliexercises/sample_input/timings.txt
cliexercises/sample_input/twos.txt
cliexercises/sample_input/varying_fields.csv
cliexercises/sample_input/backups/color list.txt
cliexercises/sample_input/backups/dot_files/.bash_aliases
cliexercises/sample_input/backups/dot_files/.inputrc
cliexercises/sample_input/backups/text/ip.txt
cliexercises-3.1.0.dist-info/METADATA
cliexercises-3.1.0.dist-info/WHEEL
cliexercises-3.1.0.dist-info/entry_points.txt
cliexercises-3.1.0.dist-info/licenses/LICENSE
cliexercises-3.1.0.dist-info/RECORD
