Metadata-Version: 2.4
Name: cliexercises
Version: 3.1.0
Summary: 70+ beginner to intermediate level questions on CLI text processing tasks
Project-URL: Source, https://github.com/learnbyexample/TUI-apps/tree/main/CLI-Exercises
Project-URL: Issues, https://github.com/learnbyexample/TUI-apps/issues
Author-email: Sundeep Agarwal <learnbyexample.net@gmail.com>
License-File: LICENSE
Classifier: License :: OSI Approved :: MIT License
Classifier: Operating System :: OS Independent
Classifier: Programming Language :: Python :: 3
Requires-Python: >=3.9
Requires-Dist: textual==0.85.2
